LICENSE
MANIFEST.in
README.md
__init__.py
setup.py
src/__init__.py
src/fgenerator/__init__.py
src/fgenerator/base.py
src/fgenerator/fparser_wrapper.py
src/fgenerator/gen.py
src/fgenerator/modify.py
src/fgenerator.egg-info/PKG-INFO
src/fgenerator.egg-info/SOURCES.txt
src/fgenerator.egg-info/dependency_links.txt
src/fgenerator.egg-info/requires.txt
src/fgenerator.egg-info/top_level.txt
src/fgenerator/tests/fgenerator_test.py
src/fgenerator/tests/utils.py